{
  "user_pools": {
    "us-east-1_JxZRAdU8m": {
      "name": "PorterCognitoPool-KltnJxCLulwK",
      "id": "us-east-1_JxZRAdU8m",
      "arn": "arn:aws:cognito-idp:us-east-1:389435993474:userpool/us-east-1_JxZRAdU8m",
      "policies": {
        "PasswordPolicy": {
          "MinimumLength": 12,
          "RequireUppercase": true,
          "RequireLowercase": true,
          "RequireNumbers": false,
          "RequireSymbols": true,
          "TemporaryPasswordValidityDays": 7
        },
        "SignInPolicy": {
          "AllowedFirstAuthFactors": [
            "PASSWORD"
          ]
        }
      },
      "mfa_configuration": "OFF",
      "tags": {}
    },
    "us-east-1_1TwGUgLb3": {
      "name": "PorterCognitoPool-vV42WGTwZwF4",
      "id": "us-east-1_1TwGUgLb3",
      "arn": "arn:aws:cognito-idp:us-east-1:389435993474:userpool/us-east-1_1TwGUgLb3",
      "policies": {
        "PasswordPolicy": {
          "MinimumLength": 12,
          "RequireUppercase": true,
          "RequireLowercase": true,
          "RequireNumbers": false,
          "RequireSymbols": true,
          "TemporaryPasswordValidityDays": 7
        },
        "SignInPolicy": {
          "AllowedFirstAuthFactors": [
            "PASSWORD"
          ]
        }
      },
      "mfa_configuration": "OFF",
      "tags": {}
    }
  },
  "user_pool_clients": {
    "7bah2n1li7uipfdacomp8njmlr": {
      "client_id": "7bah2n1li7uipfdacomp8njmlr",
      "name": "PrivateClient-AaCZwwjFHH2m",
      "user_pool_id": "us-east-1_JxZRAdU8m",
      "explicit_auth_flows": [
        "ALLOW_ADMIN_USER_PASSWORD_AUTH",
        "ALLOW_CUSTOM_AUTH",
        "ALLOW_REFRESH_TOKEN_AUTH",
        "ALLOW_USER_PASSWORD_AUTH",
        "ALLOW_USER_SRP_AUTH"
      ],
      "allowed_oauth_flows": [
        "client_credentials"
      ],
      "callback_urls": [
        "https://portal-qa.helloporter.com/authorize/callback"
      ],
      "logout_urls": [],
      "supported_identity_providers": [
        "COGNITO"
      ]
    },
    "3h3n6dv8n7iljev1oo6uds7khg": {
      "client_id": "3h3n6dv8n7iljev1oo6uds7khg",
      "name": "PublicClient-Ji7uctoTjAJF",
      "user_pool_id": "us-east-1_JxZRAdU8m",
      "explicit_auth_flows": [
        "ALLOW_CUSTOM_AUTH",
        "ALLOW_REFRESH_TOKEN_AUTH",
        "ALLOW_USER_PASSWORD_AUTH",
        "ALLOW_USER_SRP_AUTH"
      ],
      "allowed_oauth_flows": [
        "code"
      ],
      "callback_urls": [
        "https://www.jwt.io"
      ],
      "logout_urls": [],
      "supported_identity_providers": [
        "COGNITO",
        "addidp"
      ]
    },
    "7kahe66jf0vscfgapuhhvfg9ij": {
      "client_id": "7kahe66jf0vscfgapuhhvfg9ij",
      "name": "PrivateClient-IO8NVaHNlpiN",
      "user_pool_id": "us-east-1_1TwGUgLb3",
      "explicit_auth_flows": [
        "ALLOW_ADMIN_USER_PASSWORD_AUTH",
        "ALLOW_CUSTOM_AUTH",
        "ALLOW_REFRESH_TOKEN_AUTH",
        "ALLOW_USER_PASSWORD_AUTH",
        "ALLOW_USER_SRP_AUTH"
      ],
      "allowed_oauth_flows": [
        "client_credentials"
      ],
      "callback_urls": [
        "https://portal-qa.helloporter.com/authorize/callback"
      ],
      "logout_urls": [],
      "supported_identity_providers": [
        "COGNITO"
      ]
    },
    "2nsdp3b87vo810bnpmigud29ci": {
      "client_id": "2nsdp3b87vo810bnpmigud29ci",
      "name": "PublicClient-nzYqwHmM53jD",
      "user_pool_id": "us-east-1_1TwGUgLb3",
      "explicit_auth_flows": [
        "ALLOW_CUSTOM_AUTH",
        "ALLOW_REFRESH_TOKEN_AUTH",
        "ALLOW_USER_PASSWORD_AUTH",
        "ALLOW_USER_SRP_AUTH"
      ],
      "allowed_oauth_flows": [
        "code"
      ],
      "callback_urls": [
        "https://portal-qa.helloporter.com/authCallback",
        "https://portal-qa.helloporter.com/my-account/my-health-dashboard"
      ],
      "logout_urls": [],
      "supported_identity_providers": [
        "COGNITO"
      ]
    }
  },
  "identity_pools": {}
}